gpt2_prot/__init__.py
gpt2_prot/callbacks.py
gpt2_prot/data_module.py
gpt2_prot/gpt2.py
gpt2_prot/scripts/cli.py
tests/test_example.py
gpt2_prot-0.3.dist-info/LICENSE
gpt2_prot-0.3.dist-info/METADATA
gpt2_prot-0.3.dist-info/WHEEL
gpt2_prot-0.3.dist-info/entry_points.txt
gpt2_prot-0.3.dist-info/top_level.txt
gpt2_prot-0.3.dist-info/RECORD
