Metadata-Version: 2.1
Name: gpt2_prot
Version: 0.3
Summary: Single NT/AA resoultion biological GPT2 language modelling
Project-URL: Homepage, https://github.com/JBwdn/gpt2-prot
Requires-Python: >=3.10
License-File: LICENSE
Requires-Dist: biopython
Requires-Dist: jsonargparse[signatures] >=4.27.7
Requires-Dist: lightning
Requires-Dist: numpy <2.0
Requires-Dist: requests
Requires-Dist: tensorboard
Requires-Dist: torch
Requires-Dist: torcheval
Requires-Dist: tqdm
Provides-Extra: dev
Requires-Dist: black ; extra == 'dev'
Requires-Dist: ipython ; extra == 'dev'
Requires-Dist: isort ; extra == 'dev'
Requires-Dist: pre-commit ; extra == 'dev'
Requires-Dist: pylint ; extra == 'dev'
Requires-Dist: pyright ; extra == 'dev'
Requires-Dist: pytest ; extra == 'dev'
Provides-Extra: test
Requires-Dist: pytest ; extra == 'test'
